activity_log/__init__.py
activity_log/admin.py
activity_log/conf.py
activity_log/middleware.py
activity_log/models.py
activity_log/router.py
activity_log/migrations/0001_initial.py
activity_log/migrations/0002_activitylog_ip_address.py
activity_log/migrations/0003_activitylog_extra_data.py
activity_log/migrations/0004_auto_20170309_0929.py
activity_log/migrations/0005_auto_20170313_0755.py
activity_log/migrations/0006_auto_20190816_1641.py
activity_log/migrations/__init__.py
django_user_activity_log2-0.0.25.dist-info/LICENSE
django_user_activity_log2-0.0.25.dist-info/METADATA
django_user_activity_log2-0.0.25.dist-info/WHEEL
django_user_activity_log2-0.0.25.dist-info/top_level.txt
django_user_activity_log2-0.0.25.dist-info/RECORD
