Metadata-Version: 2.1
Name: django-user-activity-log2
Version: 0.0.25
Summary: HTTP queries logger with flexible filters.
Home-page: https://github.com/sebatyler/django-user-activity-log/
Author: sebatyler
Author-email: sebatyler@gmail.com
License: MIT license
Platform: UNKNOWN
Classifier: Framework :: Django
Classifier: Development Status :: 4 - Beta
Classifier: Environment :: Web Environment
Classifier: Intended Audience :: Developers
Classifier: License :: OSI Approved :: MIT License
Classifier: Programming Language :: Python
Classifier: Programming Language :: Python :: 2.7
Classifier: Programming Language :: Python :: 3.4
Classifier: Programming Language :: Python :: 3.5
Classifier: Programming Language :: Python :: 3.6
Classifier: Topic :: Software Development :: Libraries :: Python Modules
